urllink/__init__.py
urllink/core.py
urllink/utils.py
urllink-1.2.0.dist-info/licenses/LICENSE
urllink-1.2.0.dist-info/METADATA
urllink-1.2.0.dist-info/WHEEL
urllink-1.2.0.dist-info/top_level.txt
urllink-1.2.0.dist-info/RECORD
