Metadata-Version: 2.4
Name: urllink
Version: 1.2.0
Summary: A Python library for URL shortening and QR code generation.
Home-page: https://urllink.site
Author: Muhammad Hamza Shahzad
Author-email: myhamza.204@gmail.com
License-File: LICENSE
Requires-Dist: requests
Dynamic: author
Dynamic: author-email
Dynamic: description
Dynamic: description-content-type
Dynamic: home-page
Dynamic: license-file
Dynamic: requires-dist
Dynamic: summary
